polar_flow/_vendor/.gitignore
polar_flow/_vendor/README.md
polar_flow/_vendor/__init__.py
polar_flow/_vendor/pyproject.toml
polar_flow/_vendor/slurm_client/README.md
polar_flow/_vendor/slurm_client/VENDORING.txt
polar_flow/_vendor/slurm_client/__init__.py
polar_flow/_vendor/slurm_client/client.py
polar_flow/_vendor/slurm_client/errors.py
polar_flow/_vendor/slurm_client/py.typed
polar_flow/_vendor/slurm_client/types.py
polar_flow/_vendor/slurm_client/api/__init__.py
polar_flow/_vendor/slurm_client/api/slurm/__init__.py
polar_flow/_vendor/slurm_client/api/slurm/slurm_v0043_delete_job.py
polar_flow/_vendor/slurm_client/api/slurm/slurm_v0043_delete_jobs.py
polar_flow/_vendor/slurm_client/api/slurm/slurm_v0043_delete_node.py
polar_flow/_vendor/slurm_client/api/slurm/slurm_v0043_delete_reservation.py
polar_flow/_vendor/slurm_client/api/slurm/slurm_v0043_get_diag.py
polar_flow/_vendor/slurm_client/api/slurm/slurm_v0043_get_job.py
polar_flow/_vendor/slurm_client/api/slurm/slurm_v0043_get_jobs.py
polar_flow/_vendor/slurm_client/api/slurm/slurm_v0043_get_jobs_state.py
polar_flow/_vendor/slurm_client/api/slurm/slurm_v0043_get_licenses.py
polar_flow/_vendor/slurm_client/api/slurm/slurm_v0043_get_node.py
polar_flow/_vendor/slurm_client/api/slurm/slurm_v0043_get_nodes.py
polar_flow/_vendor/slurm_client/api/slurm/slurm_v0043_get_partition.py
polar_flow/_vendor/slurm_client/api/slurm/slurm_v0043_get_partitions.py
polar_flow/_vendor/slurm_client/api/slurm/slurm_v0043_get_ping.py
polar_flow/_vendor/slurm_client/api/slurm/slurm_v0043_get_reconfigure.py
polar_flow/_vendor/slurm_client/api/slurm/slurm_v0043_get_reservation.py
polar_flow/_vendor/slurm_client/api/slurm/slurm_v0043_get_reservations.py
polar_flow/_vendor/slurm_client/api/slurm/slurm_v0043_get_shares.py
polar_flow/_vendor/slurm_client/api/slurm/slurm_v0043_post_job.py
polar_flow/_vendor/slurm_client/api/slurm/slurm_v0043_post_job_allocate.py
polar_flow/_vendor/slurm_client/api/slurm/slurm_v0043_post_job_submit.py
polarflow-1.0.0.dist-info/METADATA
polarflow-1.0.0.dist-info/WHEEL
polarflow-1.0.0.dist-info/entry_points.txt
polarflow-1.0.0.dist-info/RECORD
